{
    "prepare_queue": {
        "installed": [],
        "uninstalled": []
    },
    "config_munge": {
        "files": {
            "framework": {
                "parents": {
                    "libz.dylib": [
                        {
                            "xml": "false",
                            "count": 1
                        }
                    ]
                }
            },
            "config.xml": {
                "parents": {
                    "/widget": [
                        {
                            "xml": "<feature name=\"TestFlightSDK\"><param name=\"ios-package\" value=\"CDVTestFlight\" /></feature>",
                            "count": 1
                        }
                    ]
                }
            }
        }
    },
    "installed_plugins": {
        "com.testflightapp.cordova-plugin": {
            "PACKAGE_NAME": "com.trailheadlabs.opentrails"
        }
    },
    "dependent_plugins": {}
}